{
  "artifactType": "effect_training_dossier_v1",
  "artifactVersion": "1.0",
  "generatedAt": "2026-04-17T01:05:22.821Z",
  "status": "transitional_current_evidence",
  "effectName": "Fireworks",
  "family": "particle_motion",
  "intentSurface": {
    "supportedSettingsIntent": [
      "intensity",
      "speed",
      "density",
      "coverage",
      "motion",
      "variation"
    ],
    "supportedPaletteIntent": [
      "colors",
      "temperature",
      "contrast",
      "brightness",
      "saturation",
      "accentUsage"
    ],
    "supportedLayerIntent": [
      "priority",
      "blendRole",
      "mixAmount",
      "overlayPolicy"
    ],
    "supportedRenderIntent": [
      "groupPolicy",
      "bufferStyle",
      "expansionPolicy",
      "riskTolerance"
    ]
  },
  "currentCoverage": {
    "coverageStatus": "registry_defined_not_screened",
    "exhaustiveSettingCoverage": false,
    "registryParameterNames": [
      "count",
      "explosions",
      "fade",
      "gravity",
      "velocity",
      "xLocation"
    ],
    "retainedParameterNames": [],
    "screenedParameterNames": [],
    "screeningRecordCount": 0
  },
  "upstreamMetadata": {
    "sourceFile": "Fireworks.json",
    "propertyCount": 14,
    "visibilityRuleCount": 3,
    "parameters": {
      "count": {
        "upstreamId": "Fireworks_Count",
        "label": "Particles in Explosion",
        "description": "Number of particles created in each explosion. More particles create denser, more dramatic bursts.",
        "default": 50,
        "min": 1,
        "max": 100,
        "options": []
      },
      "explosions": {
        "upstreamId": "Fireworks_Explosions",
        "label": "Number of Explosions",
        "description": "Total number of firework explosions randomly distributed across the effect duration. Disabled when using music or timing triggers.",
        "default": 16,
        "min": 1,
        "max": 50,
        "options": []
      },
      "fade": {
        "upstreamId": "Fireworks_Fade",
        "label": "Particle Fade",
        "description": "How long particles remain visible before fading out. Higher values make particles last longer.",
        "default": 50,
        "min": 1,
        "max": 100,
        "options": []
      },
      "gravity": {
        "upstreamId": "Fireworks_Gravity",
        "label": "Gravity",
        "description": "When enabled, particles arc downward over time simulating gravity. When disabled, particles fly in straight lines.",
        "default": true,
        "min": null,
        "max": null,
        "options": []
      },
      "velocity": {
        "upstreamId": "Fireworks_Velocity",
        "label": "Velocity of Particles",
        "description": "Maximum speed of particles as they fly outward from the explosion center. Higher values create larger bursts.",
        "default": 2,
        "min": 1,
        "max": 10,
        "options": []
      },
      "xLocation": {
        "upstreamId": "Fireworks_XLocation",
        "label": "X Location",
        "description": "Fixed horizontal position for explosions as a percentage of buffer width. Set to -1 for random placement.",
        "default": -1,
        "min": -1,
        "max": 100,
        "options": []
      }
    }
  },
  "registryDefinition": {
    "complexityClass": "complex",
    "earlySamplingPolicy": "broad_geometry_first",
    "notes": "Expansion-wave particle burst effect. Explosion cadence, particle count, velocity, fade, and launch placement are the primary levers. Music/timing modes are deferred.",
    "parameters": {
      "count": {
        "type": "numeric",
        "range": {
          "min": 1,
          "max": 100
        },
        "anchors": [
          10,
          30,
          50,
          75,
          100
        ],
        "importance": "high",
        "phase": "screen",
        "practicalPriority": "high",
        "stopRule": "refine_only_near_breakpoints",
        "interactionHypotheses": [
          "explosions",
          "fade"
        ],
        "upstream": {
          "id": "Fireworks_Count",
          "label": "Particles in Explosion",
          "description": "Number of particles created in each explosion. More particles create denser, more dramatic bursts.",
          "type": "int",
          "controlType": "slider",
          "default": 50,
          "min": 1,
          "max": 100,
          "divisor": 1,
          "valueCurve": true,
          "vcMin": null,
          "vcMax": null,
          "lockable": true,
          "options": [],
          "dynamicOptions": null,
          "suppressIfDefault": false
        }
      },
      "explosions": {
        "type": "numeric",
        "range": {
          "min": 1,
          "max": 50
        },
        "anchors": [
          1,
          8,
          16,
          32,
          50
        ],
        "importance": "high",
        "phase": "screen",
        "practicalPriority": "high",
        "stopRule": "stop_when_regions_stabilize",
        "interactionHypotheses": [
          "count",
          "velocity",
          "geometryProfile"
        ],
        "upstream": {
          "id": "Fireworks_Explosions",
          "label": "Number of Explosions",
          "description": "Total number of firework explosions randomly distributed across the effect duration. Disabled when using music or timing triggers.",
          "type": "int",
          "controlType": "slider",
          "default": 16,
          "min": 1,
          "max": 50,
          "divisor": 1,
          "valueCurve": false,
          "vcMin": null,
          "vcMax": null,
          "lockable": true,
          "options": [],
          "dynamicOptions": null,
          "suppressIfDefault": false
        }
      },
      "fade": {
        "type": "numeric",
        "range": {
          "min": 1,
          "max": 100
        },
        "anchors": [
          10,
          30,
          50,
          75,
          100
        ],
        "importance": "medium",
        "phase": "screen",
        "practicalPriority": "medium",
        "stopRule": "refine_only_near_breakpoints",
        "interactionHypotheses": [
          "velocity",
          "count"
        ],
        "upstream": {
          "id": "Fireworks_Fade",
          "label": "Particle Fade",
          "description": "How long particles remain visible before fading out. Higher values make particles last longer.",
          "type": "int",
          "controlType": "slider",
          "default": 50,
          "min": 1,
          "max": 100,
          "divisor": 1,
          "valueCurve": true,
          "vcMin": null,
          "vcMax": null,
          "lockable": true,
          "options": [],
          "dynamicOptions": null,
          "suppressIfDefault": false
        }
      },
      "gravity": {
        "type": "boolean",
        "anchors": [
          false,
          true
        ],
        "importance": "medium",
        "phase": "baseline",
        "practicalPriority": "medium",
        "stopRule": "all_meaningful_options",
        "interactionHypotheses": [
          "velocity"
        ],
        "upstream": {
          "id": "Fireworks_Gravity",
          "label": "Gravity",
          "description": "When enabled, particles arc downward over time simulating gravity. When disabled, particles fly in straight lines.",
          "type": "bool",
          "controlType": "checkbox",
          "default": true,
          "min": null,
          "max": null,
          "divisor": 1,
          "valueCurve": false,
          "vcMin": null,
          "vcMax": null,
          "lockable": false,
          "options": [],
          "dynamicOptions": null,
          "suppressIfDefault": false
        }
      },
      "velocity": {
        "type": "numeric",
        "range": {
          "min": 1,
          "max": 10
        },
        "anchors": [
          1,
          2,
          4,
          7,
          10
        ],
        "importance": "high",
        "phase": "screen",
        "practicalPriority": "high",
        "stopRule": "stop_when_regions_stabilize",
        "interactionHypotheses": [
          "fade",
          "gravity"
        ],
        "upstream": {
          "id": "Fireworks_Velocity",
          "label": "Velocity of Particles",
          "description": "Maximum speed of particles as they fly outward from the explosion center. Higher values create larger bursts.",
          "type": "int",
          "controlType": "slider",
          "default": 2,
          "min": 1,
          "max": 10,
          "divisor": 1,
          "valueCurve": true,
          "vcMin": null,
          "vcMax": null,
          "lockable": true,
          "options": [],
          "dynamicOptions": null,
          "suppressIfDefault": false
        }
      },
      "xLocation": {
        "type": "numeric",
        "range": {
          "min": -1,
          "max": 100
        },
        "anchors": [
          -1,
          25,
          50,
          75
        ],
        "importance": "medium",
        "phase": "screen",
        "practicalPriority": "medium",
        "stopRule": "all_meaningful_options",
        "interactionHypotheses": [
          "yLocation",
          "geometryProfile"
        ],
        "upstream": {
          "id": "Fireworks_XLocation",
          "label": "X Location",
          "description": "Fixed horizontal position for explosions as a percentage of buffer width. Set to -1 for random placement.",
          "type": "int",
          "controlType": "slider",
          "default": -1,
          "min": -1,
          "max": 100,
          "divisor": 1,
          "valueCurve": true,
          "vcMin": null,
          "vcMax": null,
          "lockable": false,
          "options": [],
          "dynamicOptions": null,
          "suppressIfDefault": false
        }
      }
    },
    "upstreamEffectName": "Fireworks",
    "upstreamSourceFile": "Fireworks.json",
    "upstreamPropertyCount": 14,
    "upstreamVisibilityRuleCount": 3,
    "upstreamSharedMetadata": [
      "Buffer",
      "Color",
      "Timing"
    ],
    "upstreamUnmappedProperties": []
  },
  "interactionCoverage": {
    "requiresInteractionCoverage": false,
    "hasInteractionCoverage": false,
    "interactionCoverageStatus": "",
    "interactionGeometries": [],
    "interactionManifestNames": []
  },
  "manifestIndex": {
    "expandedSweep": [],
    "range": [],
    "combos": [],
    "interactions": [],
    "all": []
  },
  "evidenceIndex": {
    "screeningRecords": [],
    "screeningRecordPaths": []
  },
  "currentTrainingReference": {
    "effectName": "Fireworks",
    "baseline": {
      "currentStage": "",
      "selectorReady": false,
      "selectorEvidence": {},
      "supportedModelTypes": [],
      "supportedGeometryProfiles": [],
      "intentTags": [],
      "patternFamilies": [],
      "retainedParameters": []
    },
    "capability": {
      "family": "particle_motion",
      "supportedSettingsIntent": [
        "intensity",
        "speed",
        "density",
        "coverage",
        "motion",
        "variation"
      ],
      "supportedPaletteIntent": [
        "colors",
        "temperature",
        "contrast",
        "brightness",
        "saturation",
        "accentUsage"
      ],
      "supportedLayerIntent": [
        "priority",
        "blendRole",
        "mixAmount",
        "overlayPolicy"
      ],
      "supportedRenderIntent": [
        "groupPolicy",
        "bufferStyle",
        "expansionPolicy",
        "riskTolerance"
      ]
    },
    "parameterLearning": {
      "registryParameterNames": [
        "count",
        "explosions",
        "fade",
        "gravity",
        "velocity",
        "xLocation"
      ],
      "retainedParameterNames": [],
      "supportedIntentAxes": {
        "settings": [
          "intensity",
          "speed",
          "density",
          "coverage",
          "motion",
          "variation"
        ],
        "palette": [
          "colors",
          "temperature",
          "contrast",
          "brightness",
          "saturation",
          "accentUsage"
        ],
        "layer": [
          "priority",
          "blendRole",
          "mixAmount",
          "overlayPolicy"
        ],
        "render": [
          "groupPolicy",
          "bufferStyle",
          "expansionPolicy",
          "riskTolerance"
        ]
      },
      "coverageStatus": "registry_defined_not_screened",
      "exhaustiveSettingCoverage": false,
      "screenedParameterNames": [],
      "derivedPriors": {
        "status": "empty",
        "priorCount": 0,
        "priors": []
      }
    },
    "liveOutcomeLearning": {
      "status": "seeded_empty",
      "storageClass": "general_training",
      "outcomeRecordCount": 0,
      "seedRolePriors": [],
      "roleOutcomeMemory": {
        "strengthen_lead": {
          "sampleCount": 0,
          "successfulUses": 0,
          "failedUses": 0,
          "favoredScopes": [],
          "favoredSignals": [],
          "cautionSignals": []
        },
        "reduce_competing_support": {
          "sampleCount": 0,
          "successfulUses": 0,
          "failedUses": 0,
          "favoredScopes": [],
          "favoredSignals": [],
          "cautionSignals": []
        },
        "widen_support": {
          "sampleCount": 0,
          "successfulUses": 0,
          "failedUses": 0,
          "favoredScopes": [],
          "favoredSignals": [],
          "cautionSignals": []
        },
        "increase_section_contrast": {
          "sampleCount": 0,
          "successfulUses": 0,
          "failedUses": 0,
          "favoredScopes": [],
          "favoredSignals": [],
          "cautionSignals": []
        },
        "add_section_development": {
          "sampleCount": 0,
          "successfulUses": 0,
          "failedUses": 0,
          "favoredScopes": [],
          "favoredSignals": [],
          "cautionSignals": []
        }
      },
      "parameterOutcomeMemory": {},
      "sharedSettingOutcomeMemory": {}
    },
    "screeningLearning": {
      "status": "empty",
      "storageClass": "general_training",
      "screeningRecordCount": 0,
      "screenedParameterNames": [],
      "sampledModelTypes": [],
      "sampledGeometryProfiles": [],
      "observedLabelHints": [],
      "configurationRepresentativeness": {
        "coverageStatus": "none",
        "profileCount": 0,
        "profiles": []
      }
    }
  }
}
